<?xml version="1.0" encoding="UTF-8" standalone="no"?>
<!DOCTYPE experiment SYSTEM "DTDFILE_FULLPATH">
<experiment version="1.1.0">
	<experimentViews>
		<tab name="Tab_1">
			<plotWindow title="Plot_2" x="0" y="311" dx="990" dy="311">
				<plot id="Plot_2">
					<axeX variableName="TIME">
						<scale min="0" max="20"/>
						<titleAxe value="TIME"/>
					</axeX>
					<axeY>
						<scale min="0.005" max="0.05"/>
						<titleAxe value=""/>
					</axeY>
					<title value="Plot_2" isShowed="false">
						<font size="10"/>
					</title>
					<canvas>
						<majorGrid  lineType="dot" lineColor="160,160,164"/>
						<minorGrid  lineType="dot" lineColor="160,160,164"/>
					</canvas>
					<chartStyles>
						<var name="state_out.alpha" nick="state_out.alpha" lineColor="255,0,0"/>
						<var name="state_out.theta" nick="state_out.theta" lineColor="0,204,153"/>
					</chartStyles>
				</plot>
			</plotWindow>
			<plotWindow title="Plot_1" x="0" y="0" dx="990" dy="311">
				<plot id="Plot_1">
					<axeX variableName="TIME">
						<titleAxe value="TIME"/>
					</axeX>
					<axeY>
						<titleAxe value=""/>
					</axeY>
					<title value="Plot_1" isShowed="false">
						<font size="10"/>
					</title>
					<canvas>
						<majorGrid  lineType="dot" lineColor="160,160,164"/>
						<minorGrid  lineType="dot" lineColor="160,160,164"/>
					</canvas>
					<chartStyles>
						<var name="Aero.elevator" nick="Aero.elevator" lineColor="255,0,0"/>
					</chartStyles>
				</plot>
			</plotWindow>
		</tab>
	</experimentViews>
	<watch width="278" visible="true">
	</watch>
	<outputWindow height="252" visible="true"/>
</experiment>